lic/.mypy_cache/.gitignore
lic/.mypy_cache/3.7/@plugins_snapshot.json
lic/.mypy_cache/3.7/_ast.data.json
lic/.mypy_cache/3.7/_ast.meta.json
lic/.mypy_cache/3.7/_importlib_modulespec.data.json
lic/.mypy_cache/3.7/_importlib_modulespec.meta.json
lic/.mypy_cache/3.7/_typeshed/__init__.data.json
lic/.mypy_cache/3.7/_typeshed/__init__.meta.json
lic/.mypy_cache/3.7/abc.data.json
lic/.mypy_cache/3.7/abc.meta.json
lic/.mypy_cache/3.7/argparse.data.json
lic/.mypy_cache/3.7/argparse.meta.json
lic/.mypy_cache/3.7/array.data.json
lic/.mypy_cache/3.7/array.meta.json
lic/.mypy_cache/3.7/ast.data.json
lic/.mypy_cache/3.7/ast.meta.json
lic/.mypy_cache/3.7/builtins.data.json
lic/.mypy_cache/3.7/builtins.meta.json
lic/.mypy_cache/3.7/codecs.data.json
lic/.mypy_cache/3.7/codecs.meta.json
lic/.mypy_cache/3.7/collections/__init__.data.json
lic/.mypy_cache/3.7/collections/__init__.meta.json
lic/.mypy_cache/3.7/ctypes/__init__.data.json
lic/.mypy_cache/3.7/ctypes/__init__.meta.json
lic/.mypy_cache/3.7/enum.data.json
lic/.mypy_cache/3.7/enum.meta.json
lic/.mypy_cache/3.7/genericpath.data.json
lic/.mypy_cache/3.7/genericpath.meta.json
lic/.mypy_cache/3.7/importlib/__init__.data.json
lic/.mypy_cache/3.7/importlib/__init__.meta.json
lic/.mypy_cache/3.7/importlib/abc.data.json
lic/.mypy_cache/3.7/importlib/abc.meta.json
lic/.mypy_cache/3.7/io.data.json
lic/.mypy_cache/3.7/io.meta.json
lic/.mypy_cache/3.7/lic/__init__.data.json
lic/.mypy_cache/3.7/lic/__init__.meta.json
lic/.mypy_cache/3.7/lic/lic.data.json
lic/.mypy_cache/3.7/lic/lic.meta.json
lic/.mypy_cache/3.7/logging/__init__.data.json
lic/.mypy_cache/3.7/logging/__init__.meta.json
lic/.mypy_cache/3.7/mmap.data.json
lic/.mypy_cache/3.7/mmap.meta.json
lic/.mypy_cache/3.7/multiprocessing/__init__.data.json
lic/.mypy_cache/3.7/multiprocessing/__init__.meta.json
lic/.mypy_cache/3.7/multiprocessing/connection.data.json
lic/.mypy_cache/3.7/multiprocessing/connection.meta.json
lic/.mypy_cache/3.7/multiprocessing/context.data.json
lic-0.4.5.dist-info/entry_points.txt
lic-0.4.5.dist-info/LICENSE
lic-0.4.5.dist-info/WHEEL
lic-0.4.5.dist-info/METADATA
lic-0.4.5.dist-info/RECORD
