Metadata-Version: 2.1
Name: lic
Version: 0.4.5
Summary: Line integral convolution for numpy arrays
Home-page: https://gitlab.com/szs/lic/
License: MIT
Keywords: flow field,vector field,visualisation,CFD,plot
Author: Steffen Brinkmann
Author-email: s-b@mailbox.org
Requires-Python: >=3.6.1,<4.0.0
Classifier: Development Status :: 4 - Beta
Classifier: Intended Audience :: Science/Research
Classifier: License :: OSI Approved :: MIT License
Classifier: Programming Language :: Python :: 3
Classifier: Programming Language :: Python :: 3.6
Classifier: Programming Language :: Python :: 3.7
Classifier: Programming Language :: Python :: 3.8
Classifier: Programming Language :: Python :: 3.9
Classifier: Topic :: Scientific/Engineering
Classifier: Topic :: Scientific/Engineering :: Visualization
Requires-Dist: imageio (>=2.8.0,<3.0.0)
Requires-Dist: matplotlib (>=3.2.1,<4.0.0)
Requires-Dist: numpy (>=1.18.5,<2.0.0)
Requires-Dist: tqdm (>=4.47.0,<5.0.0)
Project-URL: Documentation, https://lic.readthedocs.io/en/latest/
Project-URL: Repository, https://gitlab.com/szs/lic/
